{
  "id": "24-7-ERROR-DETECTION-ROUTINE",
  "version": "1.0.0-PERMANENT",
  "status": "PERMANENT-ACTIVE",
  "mandatory": true,
  "hardCoded": true,
  "sealedWith": "TTT-HORIZONTAL-BAR-INFINITY",
  "branding": ".{T,.[ OS.] OS-TOS - OSTOS∞8∞+++a∞:=n→∞lim​an∞ as superscript ≈ ⁺∞(C)(R) | URL: TEL1.NL - WHATSAPP - ( 0031613803782 ). T,.&T,,.&T,,,.].T,,,,.(C)(R).T,,.}.",
  "description": "PERMANENTE 24/7 FEHLERERKENNUNGS-ROUTINE - Erkennt Fehler bevor sie entstehen. Läuft 24 Stunden, 7 Tage die Woche durch die Settings-Ordner fehlerfrei. Es darf kein einziger Fehlercode entstehen.",
  "principle": "KEIN EINZIGER FEHLERCODE SOLL ENTSTEHEN. 24/7 Fehlererkennung durch Settings-Ordner. Alle Settings, Power und Sprachmodelle zur Fehlererkennung einsetzen.",
  "workflow": {
    "pre": [
      "loadAllSettings",
      "activateAllMCPs",
      "runPreCodeVerification",
      "runPatternMatching",
      "runCrossPlatformValidation",
      "runNeuronalDimensionalAnalysis",
      "predictErrors"
    ],
    "during": [
      "continuousErrorDetection",
      "realTimePatternMatching",
      "errorPrevention",
      "autoFixIntegration",
      "crossPlatformMonitoring"
    ],
    "post": [
      "runAllTests",
      "verifyNoErrors",
      "updateErrorPatterns",
      "updateNeuronalModel",
      "logErrorPrevention"
    ]
  },
  "errorDetection": {
    "enabled": true,
    "frequency": "continuous",
    "methods": [
      "patternMatching",
      "codeAnalysis",
      "crossPlatformTesting",
      "neuronalPrediction",
      "settingsValidation"
    ],
    "sources": [
      "Settings/INDUSTRIAL-FABRICATION-ROUTINE.json",
      "Settings/PRE-CODE-VERIFICATION-SYSTEM.json",
      "Settings/CONSOLE-MONITORING-SYSTEM.json",
      "Settings/PERMANENT-TEST-ROUTINE.json",
      "Settings/MASTER-SETTINGS-SYSTEM.json",
      "Settings/USER-FRIENDLINESS-ROUTINE.json"
    ]
  },
  "patternMatching": {
    "enabled": true,
    "patternsPath": "Settings/error-patterns.json",
    "knownErrors": [
      {
        "pattern": "return.*without.*error.*message",
        "description": "Silent Error Handling - Setup bricht ohne Fehlermeldung ab",
        "fix": "Add error message and user feedback",
        "prevented": true
      },
      {
        "pattern": "findSettingsFolder.*return.*\"\"",
        "description": "Settings nicht gefunden - Setup bricht ab",
        "fix": "Add fallback with default settings",
        "prevented": true
      },
      {
        "pattern": "findOSTOSOSSource.*return.*\"\"",
        "description": "OSTOSOS-Dateien nicht gefunden - Setup bricht ab",
        "fix": "Add minimal installation fallback",
        "prevented": true
      },
      {
        "pattern": "os\\.Exit\\(0\\)|return.*silent",
        "description": "Silent Exit ohne User-Feedback",
        "fix": "Add pause and user feedback",
        "prevented": true
      }
    ]
  },
  "crossPlatformValidation": {
    "enabled": true,
    "platforms": ["windows", "macos", "linux"],
    "testOnAllPlatforms": true,
    "compareBuilds": true,
    "detectPlatformSpecificErrors": true
  },
  "autoFix": {
    "enabled": true,
    "templatesPath": "Settings/auto-fix-templates.json",
    "applyFixesAutomatically": true,
    "verifyFixes": true,
    "logFixes": true
  },
  "monitoring": {
    "enabled": true,
    "frequency": "24/7",
    "continuous": true,
    "codeScanning": true,
    "buildMonitoring": true,
    "testAutomation": true,
    "errorLogging": true
  },
  "integration": {
    "industrialFabrication": "Settings/INDUSTRIAL-FABRICATION-ROUTINE.json",
    "preCodeVerification": "Settings/PRE-CODE-VERIFICATION-SYSTEM.json",
    "consoleMonitoring": "Settings/CONSOLE-MONITORING-SYSTEM.json",
    "permanentTestRoutine": "Settings/PERMANENT-TEST-ROUTINE.json",
    "masterSettings": "Settings/MASTER-SETTINGS-SYSTEM.json",
    "userFriendliness": "Settings/USER-FRIENDLINESS-ROUTINE.json"
  },
  "power": {
    "allSettings": true,
    "allMCPs": true,
    "allLanguageModels": true,
    "neuronalDimensionalAnalysis": true,
    "errorPrediction": true
  },
  "guardRules": {
    "noErrorCodes": {
      "enabled": true,
      "description": "Es darf kein einziger Fehlercode entstehen",
      "mandatory": true,
      "cannotBeDisabled": true
    },
    "24-7Monitoring": {
      "enabled": true,
      "description": "24/7 Fehlererkennung durch Settings-Ordner",
      "mandatory": true,
      "cannotBeDisabled": true
    },
    "errorPrevention": {
      "enabled": true,
      "description": "Fehler werden verhindert bevor sie entstehen",
      "mandatory": true,
      "cannotBeDisabled": true
    }
  }
}

